setup.py
Wintx.egg-info/PKG-INFO
Wintx.egg-info/SOURCES.txt
Wintx.egg-info/dependency_links.txt
Wintx.egg-info/requires.txt
Wintx.egg-info/top_level.txt
wintx/Fastener.py
wintx/Wintx.py
wintx/__init__.py
wintx/errors.py
wintx/drivers/__init__.py
wintx/drivers/dummy/Config.py
wintx/drivers/dummy/Driver.py
wintx/drivers/dummy/__init__.py
wintx/importers/__init__.py
wintx/interfaces/Deleter.py
wintx/interfaces/Importer.py
wintx/interfaces/Interface.py
wintx/interfaces/Query.py
wintx/interfaces/__init__.py