Metadata-Version: 1.0
Name: Wintx
Version: 2.0.0
Summary: A sharded meteorological database.
Home-page: UNKNOWN
Author: Seth Cook
Author-email: cook71@purdue.edu
License: UNKNOWN
Platform: UNKNOWN
Classifier: Programming Language :: Python :: 2.6
Classifier: Operating System :: Unix
Classifier: Development Status :: 5 - Production/Stable
